Metadata-Version: 2.1
Name: utilsForWindows
Version: 0.2.0
Summary: Simple toolset for windows
Home-page: UNKNOWN
Author: BlueLvRen
Author-email: l1401470134@163.com
License: UNKNOWN
Platform: UNKNOWN
Classifier: Intended Audience :: Developers
Classifier: Programming Language :: Python :: 3.9
